django_social_launch/forms.py
django_social_launch/views.py
django_social_launch/models.py
django_social_launch/pipeline.py
django_social_launch/urls.py
django_social_launch/__init__.py
django_social_launch/tests/test_pipeline.py
django_social_launch/tests/test_urls.py
django_social_launch/tests/base.py
django_social_launch/tests/__init__.py
django_social_launch/templates/social_launch/index.html
django_social_launch/templates/social_launch/base.html
django_social_launch_test_project/settings.py
django_social_launch_test_project/wsgi.py
django_social_launch_test_project/local_settings.py
django_social_launch_test_project/urls.py
django_social_launch_test_project/__init__.py
django_social_launch_test_project/runtests.py
django_social_launch_test_project/templates/404.html
django_social_launch_test_project/templates/base.html
django_social_launch-0.1.4.dist-info/DESCRIPTION.rst
django_social_launch-0.1.4.dist-info/RECORD
django_social_launch-0.1.4.dist-info/metadata.json
django_social_launch-0.1.4.dist-info/WHEEL
django_social_launch-0.1.4.dist-info/METADATA
django_social_launch-0.1.4.dist-info/top_level.txt
