Metadata-Version: 2.0
Name: django-social-launch
Version: 0.1.4
Summary: Social sign up page for Django.
Home-page: http://seanhayes.name/
Author: Seán Hayes
Author-email: sean@seanhayes.name
License: GPL
Download-URL: https://github.com/SeanHayes/django-social-launch
Keywords: django social sign up referrer
Platform: UNKNOWN
Classifier: Development Status :: 3 - Alpha
Classifier: Framework :: Django
Classifier: Intended Audience :: Developers
Classifier: License :: OSI Approved :: GNU General Public License (GPL)
Classifier: Operating System :: OS Independent
Classifier: Programming Language :: Python
Classifier: Programming Language :: Python :: 2.7
Classifier: Topic :: Internet :: WWW/HTTP :: Dynamic Content
Classifier: Topic :: Internet :: WWW/HTTP :: Site Management
Classifier: Topic :: Software Development :: Libraries
Classifier: Topic :: Software Development :: Libraries :: Python Modules
Requires-Dist: Django (>=1.7)
Requires-Dist: python-social-auth
